alpha2aleph/cfgini.py
alpha2aleph/cmdline.py
alpha2aleph/fb1d_fb4f.py
alpha2aleph/glob.py
alpha2aleph/globalsrtl.py
alpha2aleph/improve_rtlalphatext.py
alpha2aleph/logger.py
alpha2aleph/main.py
alpha2aleph/regex.py
alpha2aleph/utils.py
alpha2aleph-0.3.1.dist-info/DESCRIPTION.rst
alpha2aleph-0.3.1.dist-info/METADATA
alpha2aleph-0.3.1.dist-info/RECORD
alpha2aleph-0.3.1.dist-info/WHEEL
alpha2aleph-0.3.1.dist-info/entry_points.txt
alpha2aleph-0.3.1.dist-info/metadata.json
alpha2aleph-0.3.1.dist-info/top_level.txt
