Metadata-Version: 2.0
Name: alpha2aleph
Version: 0.3.1
Summary: GPLv3/Python3/CLI script to convert something like 'mlḵ' in 'כלמ'
Home-page: https://github.com/suizokukan/alpha2aleph
Author: Xavier Faure (suizokukan / 94.23.197.37)
Author-email: suizokukan@orange.fr
License: GPL-3.0
Keywords: text hebrew translitteration
Platform: UNKNOWN
Classifier: Development Status :: 2 - Pre-Alpha
Classifier: Intended Audience :: Education
Classifier: Topic :: Utilities
Classifier: License :: OSI Approved :: GNU General Public License v3 (GPLv3)
Classifier: Programming Language :: Python :: 3
